{
    "description": "",
    "tags": [],
    "size": {
        "height": 2322,
        "width": 4128
    },
    "objects": [
        {
            "id": 14416778,
            "classId": 20747,
            "description": "",
            "geometryType": "polygon",
            "labelerLogin": "gr@datasetninja.com",
            "createdAt": "2023-07-11T09:24:46.743Z",
            "updatedAt": "2023-07-11T09:24:46.743Z",
            "tags": [],
            "classTitle": "healthy",
            "points": {
                "exterior": [
                    [
                        176,
                        1295
                    ],
                    [
                        459,
                        1145
                    ],
                    [
                        883,
                        1050
                    ],
                    [
                        1196,
                        1003
                    ],
                    [
                        1483,
                        926
                    ],
                    [
                        1805,
                        840
                    ],
                    [
                        2036,
                        755
                    ],
                    [
                        2118,
                        742
                    ],
                    [
                        2349,
                        643
                    ],
                    [
                        2512,
                        660
                    ],
                    [
                        2607,
                        725
                    ],
                    [
                        2727,
                        690
                    ],
                    [
                        2512,
                        866
                    ],
                    [
                        2306,
                        982
                    ],
                    [
                        2195,
                        1162
                    ],
                    [
                        2126,
                        1235
                    ],
                    [
                        2002,
                        1205
                    ],
                    [
                        1766,
                        1269
                    ],
                    [
                        1595,
                        1308
                    ],
                    [
                        1505,
                        1415
                    ],
                    [
                        1385,
                        1376
                    ],
                    [
                        1235,
                        1393
                    ],
                    [
                        1192,
                        1428
                    ],
                    [
                        1085,
                        1393
                    ],
                    [
                        1003,
                        1428
                    ],
                    [
                        926,
                        1440
                    ],
                    [
                        767,
                        1385
                    ],
                    [
                        454,
                        1368
                    ]
                ],
                "interior": []
            }
        }
    ]
}