{
    "description": "",
    "tags": [],
    "size": {
        "height": 2322,
        "width": 4128
    },
    "objects": [
        {
            "id": 14418368,
            "classId": 20747,
            "description": "",
            "geometryType": "polygon",
            "labelerLogin": "gr@datasetninja.com",
            "createdAt": "2023-07-11T09:25:48.373Z",
            "updatedAt": "2023-07-11T09:25:48.373Z",
            "tags": [],
            "classTitle": "healthy",
            "points": {
                "exterior": [
                    [
                        622,
                        1483
                    ],
                    [
                        729,
                        1316
                    ],
                    [
                        952,
                        1265
                    ],
                    [
                        1256,
                        1072
                    ],
                    [
                        1350,
                        1055
                    ],
                    [
                        1475,
                        1055
                    ],
                    [
                        1621,
                        947
                    ],
                    [
                        1788,
                        909
                    ],
                    [
                        1856,
                        969
                    ],
                    [
                        2036,
                        952
                    ],
                    [
                        2139,
                        1016
                    ],
                    [
                        2414,
                        900
                    ],
                    [
                        2632,
                        926
                    ],
                    [
                        2838,
                        1115
                    ],
                    [
                        2945,
                        1093
                    ],
                    [
                        3052,
                        1063
                    ],
                    [
                        3241,
                        1140
                    ],
                    [
                        3425,
                        1218
                    ],
                    [
                        3588,
                        1282
                    ],
                    [
                        3271,
                        1303
                    ],
                    [
                        3142,
                        1492
                    ],
                    [
                        2984,
                        1569
                    ],
                    [
                        2825,
                        1556
                    ],
                    [
                        2581,
                        1689
                    ],
                    [
                        2422,
                        1578
                    ],
                    [
                        2246,
                        1578
                    ],
                    [
                        2152,
                        1625
                    ],
                    [
                        2002,
                        1573
                    ],
                    [
                        1912,
                        1612
                    ],
                    [
                        1835,
                        1685
                    ],
                    [
                        1711,
                        1676
                    ],
                    [
                        1526,
                        1608
                    ],
                    [
                        1406,
                        1642
                    ],
                    [
                        1299,
                        1723
                    ],
                    [
                        1132,
                        1685
                    ],
                    [
                        1037,
                        1616
                    ],
                    [
                        870,
                        1651
                    ],
                    [
                        703,
                        1573
                    ]
                ],
                "interior": []
            }
        }
    ]
}